rasberrysoup/__init__.py
rasberrysoup-1.0.0.dist-info/licenses/LICENSE
rasberrysoup-1.0.0.dist-info/METADATA
rasberrysoup-1.0.0.dist-info/WHEEL
rasberrysoup-1.0.0.dist-info/top_level.txt
rasberrysoup-1.0.0.dist-info/RECORD
