Metadata-Version: 2.4
Name: rasberrysoup
Version: 1.0.0
Summary: A Python library for simplifying complex mathematical formulas with simple keyword calls.
Author-email: "Rheehose (Rhee Creative)" <sea35652@gmail.com>
License: MIT
Keywords: math,mathematics,formula,engineering,science
Classifier: Programming Language :: Python :: 3
Classifier: License :: OSI Approved :: MIT License
Classifier: Operating System :: OS Independent
Requires-Python: >=3.8
License-File: LICENSE
Dynamic: license-file
